[
    {
        "id":"1261198574421000193",
        "delFlag":false,
        "crtTime":"2020-05-15 02:35:47",
        "version":1,
        "budgetName":"2018年-XXX市决算",
        "year":2018,
        "area":"XXX市",
        "attaRealPath":"741833a4e1b83461ef5ceeffd92ecf7e.xls",
        "budgetType":"一般公共预算",
        "fundType":"支出",
        "budgetSubject":"一、一般公共服务支出",
        "budgetSubjectLevel":0,
        "budgetNum":182120,
        "budgetAdjustNum":298882,
        "budgetFinalNum":253882,
        "makeLevel":"totalLv"
    },
    {
        "id":"1261198574437777409",
        "delFlag":false,
        "crtTime":"2020-05-15 02:35:47",
        "version":1,
        "budgetName":"2018年-XXX市决算",
        "year":2018,
        "area":"XXX市",
        "attaRealPath":"741833a4e1b83461ef5ceeffd92ecf7e.xls",
        "budgetType":"一般公共预算",
        "fundType":"支出",
        "budgetSubject":"二、外交支出",
        "budgetSubjectLevel":0,
        "budgetNum":356,
        "budgetAdjustNum":387,
        "budgetFinalNum":387,
        "makeLevel":"totalLv"
    },
    {
        "id":"1261198574471331842",
        "delFlag":false,
        "crtTime":"2020-05-15 02:35:47",
        "version":1,
        "budgetName":"2018年-XXX市决算",
        "year":2018,
        "area":"XXX市",
        "attaRealPath":"741833a4e1b83461ef5ceeffd92ecf7e.xls",
        "budgetType":"一般公共预算",
        "fundType":"支出",
        "budgetSubject":"三、国防支出",
        "budgetSubjectLevel":0,
        "budgetNum":176,
        "budgetAdjustNum":188,
        "budgetFinalNum":188,
        "makeLevel":"totalLv"
    },
    {
        "id":"1261198574504886274",
        "delFlag":false,
        "crtTime":"2020-05-15 02:35:47",
        "version":1,
        "budgetName":"2018年-XXX市决算",
        "year":2018,
        "area":"XXX市",
        "attaRealPath":"741833a4e1b83461ef5ceeffd92ecf7e.xls",
        "budgetType":"一般公共预算",
        "fundType":"支出",
        "budgetSubject":"四、公共安全支出",
        "budgetSubjectLevel":0,
        "budgetNum":118568,
        "budgetAdjustNum":144692,
        "budgetFinalNum":144692,
        "makeLevel":"totalLv"
    },
    {
        "id":"1261198574525857794",
        "delFlag":false,
        "crtTime":"2020-05-15 02:35:47",
        "version":1,
        "budgetName":"2018年-XXX市决算",
        "year":2018,
        "area":"XXX市",
        "attaRealPath":"741833a4e1b83461ef5ceeffd92ecf7e.xls",
        "budgetType":"一般公共预算",
        "fundType":"支出",
        "budgetSubject":"五、教育支出",
        "budgetSubjectLevel":0,
        "budgetNum":283070,
        "budgetAdjustNum":339650,
        "budgetFinalNum":336871,
        "makeLevel":"totalLv"
    },
    {
        "id":"1261198574546829314",
        "delFlag":false,
        "crtTime":"2020-05-15 02:35:47",
        "version":1,
        "budgetName":"2018年-XXX市决算",
        "year":2018,
        "area":"XXX市",
        "attaRealPath":"741833a4e1b83461ef5ceeffd92ecf7e.xls",
        "budgetType":"一般公共预算",
        "fundType":"支出",
        "budgetSubject":"六、科学技术支出",
        "budgetSubjectLevel":0,
        "budgetNum":3651,
        "budgetAdjustNum":2587,
        "budgetFinalNum":2587,
        "makeLevel":"totalLv"
    },
    {
        "id":"1261198574563606530",
        "delFlag":false,
        "crtTime":"2020-05-15 02:35:47",
        "version":1,
        "budgetName":"2018年-XXX市决算",
        "year":2018,
        "area":"XXX市",
        "attaRealPath":"741833a4e1b83461ef5ceeffd92ecf7e.xls",
        "budgetType":"一般公共预算",
        "fundType":"支出",
        "budgetSubject":"七、文化体育与传媒支出",
        "budgetSubjectLevel":0,
        "budgetNum":30711,
        "budgetAdjustNum":44552,
        "budgetFinalNum":44552,
        "makeLevel":"totalLv"
    },
    {
        "id":"1261198574584578050",
        "delFlag":false,
        "crtTime":"2020-05-15 02:35:47",
        "version":1,
        "budgetName":"2018年-XXX市决算",
        "year":2018,
        "area":"XXX市",
        "attaRealPath":"741833a4e1b83461ef5ceeffd92ecf7e.xls",
        "budgetType":"一般公共预算",
        "fundType":"支出",
        "budgetSubject":"八、社会保障和就业支出",
        "budgetSubjectLevel":0,
        "budgetNum":95239,
        "budgetAdjustNum":147275,
        "budgetFinalNum":147275,
        "makeLevel":"totalLv"
    },
    {
        "id":"1261198574605549570",
        "delFlag":false,
        "crtTime":"2020-05-15 02:35:47",
        "version":1,
        "budgetName":"2018年-XXX市决算",
        "year":2018,
        "area":"XXX市",
        "attaRealPath":"741833a4e1b83461ef5ceeffd92ecf7e.xls",
        "budgetType":"一般公共预算",
        "fundType":"支出",
        "budgetSubject":"九、医疗卫生与计划生育支出",
        "budgetSubjectLevel":0,
        "budgetNum":90163,
        "budgetAdjustNum":130047,
        "budgetFinalNum":130047,
        "makeLevel":"totalLv"
    },
    {
        "id":"1261198574622326786",
        "delFlag":false,
        "crtTime":"2020-05-15 02:35:47",
        "version":1,
        "budgetName":"2018年-XXX市决算",
        "year":2018,
        "area":"XXX市",
        "attaRealPath":"741833a4e1b83461ef5ceeffd92ecf7e.xls",
        "budgetType":"一般公共预算",
        "fundType":"支出",
        "budgetSubject":"十、节能环保支出",
        "budgetSubjectLevel":0,
        "budgetNum":14721,
        "budgetAdjustNum":62713,
        "budgetFinalNum":62713,
        "makeLevel":"totalLv"
    },
    {
        "id":"1261198574634909697",
        "delFlag":false,
        "crtTime":"2020-05-15 02:35:47",
        "version":1,
        "budgetName":"2018年-XXX市决算",
        "year":2018,
        "area":"XXX市",
        "attaRealPath":"741833a4e1b83461ef5ceeffd92ecf7e.xls",
        "budgetType":"一般公共预算",
        "fundType":"支出",
        "budgetSubject":"十一、城乡社区支出",
        "budgetSubjectLevel":0,
        "budgetNum":131976,
        "budgetAdjustNum":157610,
        "budgetFinalNum":157610,
        "makeLevel":"totalLv"
    },
    {
        "id":"1261198574647492609",
        "delFlag":false,
        "crtTime":"2020-05-15 02:35:47",
        "version":1,
        "budgetName":"2018年-XXX市决算",
        "year":2018,
        "area":"XXX市",
        "attaRealPath":"741833a4e1b83461ef5ceeffd92ecf7e.xls",
        "budgetType":"一般公共预算",
        "fundType":"支出",
        "budgetSubject":"十二、农林水支出",
        "budgetSubjectLevel":0,
        "budgetNum":320193,
        "budgetAdjustNum":669467,
        "budgetFinalNum":645317,
        "makeLevel":"totalLv"
    },
    {
        "id":"1261198574668464130",
        "delFlag":false,
        "crtTime":"2020-05-15 02:35:47",
        "version":1,
        "budgetName":"2018年-XXX市决算",
        "year":2018,
        "area":"XXX市",
        "attaRealPath":"741833a4e1b83461ef5ceeffd92ecf7e.xls",
        "budgetType":"一般公共预算",
        "fundType":"支出",
        "budgetSubject":"十三、交通运输支出",
        "budgetSubjectLevel":0,
        "budgetNum":116475,
        "budgetAdjustNum":205653,
        "budgetFinalNum":205653,
        "makeLevel":"totalLv"
    },
    {
        "id":"1261198574681047042",
        "delFlag":false,
        "crtTime":"2020-05-15 02:35:47",
        "version":1,
        "budgetName":"2018年-XXX市决算",
        "year":2018,
        "area":"XXX市",
        "attaRealPath":"741833a4e1b83461ef5ceeffd92ecf7e.xls",
        "budgetType":"一般公共预算",
        "fundType":"支出",
        "budgetSubject":"十四、资源勘探信息等支出",
        "budgetSubjectLevel":0,
        "budgetNum":8586,
        "budgetAdjustNum":17313,
        "budgetFinalNum":17313,
        "makeLevel":"totalLv"
    },
    {
        "id":"1261198574697824257",
        "delFlag":false,
        "crtTime":"2020-05-15 02:35:47",
        "version":1,
        "budgetName":"2018年-XXX市决算",
        "year":2018,
        "area":"XXX市",
        "attaRealPath":"741833a4e1b83461ef5ceeffd92ecf7e.xls",
        "budgetType":"一般公共预算",
        "fundType":"支出",
        "budgetSubject":"十五、商业服务业等支出",
        "budgetSubjectLevel":0,
        "budgetNum":6318,
        "budgetAdjustNum":11714,
        "budgetFinalNum":11714,
        "makeLevel":"totalLv"
    },
    {
        "id":"1261198574710407170",
        "delFlag":false,
        "crtTime":"2020-05-15 02:35:47",
        "version":1,
        "budgetName":"2018年-XXX市决算",
        "year":2018,
        "area":"XXX市",
        "attaRealPath":"741833a4e1b83461ef5ceeffd92ecf7e.xls",
        "budgetType":"一般公共预算",
        "fundType":"支出",
        "budgetSubject":"十六、金融支出",
        "budgetSubjectLevel":0,
        "budgetNum":0,
        "budgetAdjustNum":0,
        "budgetFinalNum":0,
        "makeLevel":"totalLv"
    },
    {
        "id":"1261198574718795779",
        "delFlag":false,
        "crtTime":"2020-05-15 02:35:47",
        "version":1,
        "budgetName":"2018年-XXX市决算",
        "year":2018,
        "area":"XXX市",
        "attaRealPath":"741833a4e1b83461ef5ceeffd92ecf7e.xls",
        "budgetType":"一般公共预算",
        "fundType":"支出",
        "budgetSubject":"十七、援助其他地区支出",
        "budgetSubjectLevel":0,
        "budgetNum":423,
        "budgetAdjustNum":0,
        "budgetFinalNum":0,
        "makeLevel":"totalLv"
    },
    {
        "id":"1261198574727184385",
        "delFlag":false,
        "crtTime":"2020-05-15 02:35:47",
        "version":1,
        "budgetName":"2018年-XXX市决算",
        "year":2018,
        "area":"XXX市",
        "attaRealPath":"741833a4e1b83461ef5ceeffd92ecf7e.xls",
        "budgetType":"一般公共预算",
        "fundType":"支出",
        "budgetSubject":"十八、国土海洋气象等支出",
        "budgetSubjectLevel":0,
        "budgetNum":17568,
        "budgetAdjustNum":18716,
        "budgetFinalNum":18716,
        "makeLevel":"totalLv"
    },
    {
        "id":"1261198574743961601",
        "delFlag":false,
        "crtTime":"2020-05-15 02:35:47",
        "version":1,
        "budgetName":"2018年-XXX市决算",
        "year":2018,
        "area":"XXX市",
        "attaRealPath":"741833a4e1b83461ef5ceeffd92ecf7e.xls",
        "budgetType":"一般公共预算",
        "fundType":"支出",
        "budgetSubject":"十九、住房保障支出",
        "budgetSubjectLevel":0,
        "budgetNum":22826,
        "budgetAdjustNum":111649,
        "budgetFinalNum":88254,
        "makeLevel":"totalLv"
    },
    {
        "id":"1261198574760738817",
        "delFlag":false,
        "crtTime":"2020-05-15 02:35:47",
        "version":1,
        "budgetName":"2018年-XXX市决算",
        "year":2018,
        "area":"XXX市",
        "attaRealPath":"741833a4e1b83461ef5ceeffd92ecf7e.xls",
        "budgetType":"一般公共预算",
        "fundType":"支出",
        "budgetSubject":"二十、粮油物资储备支出",
        "budgetSubjectLevel":0,
        "budgetNum":607,
        "budgetAdjustNum":2377,
        "budgetFinalNum":2377,
        "makeLevel":"totalLv"
    },
    {
        "id":"1261198574769127425",
        "delFlag":false,
        "crtTime":"2020-05-15 02:35:47",
        "version":1,
        "budgetName":"2018年-XXX市决算",
        "year":2018,
        "area":"XXX市",
        "attaRealPath":"741833a4e1b83461ef5ceeffd92ecf7e.xls",
        "budgetType":"一般公共预算",
        "fundType":"支出",
        "budgetSubject":"二十一、预备费",
        "budgetSubjectLevel":0,
        "budgetNum":9545,
        "budgetAdjustNum":0,
        "budgetFinalNum":0,
        "makeLevel":"totalLv"
    },
    {
        "id":"1261198574785904641",
        "delFlag":false,
        "crtTime":"2020-05-15 02:35:47",
        "version":1,
        "budgetName":"2018年-XXX市决算",
        "year":2018,
        "area":"XXX市",
        "attaRealPath":"741833a4e1b83461ef5ceeffd92ecf7e.xls",
        "budgetType":"一般公共预算",
        "fundType":"支出",
        "budgetSubject":"二十二、其他支出",
        "budgetSubjectLevel":0,
        "budgetNum":36922,
        "budgetAdjustNum":33782,
        "budgetFinalNum":33782,
        "makeLevel":"totalLv"
    },
    {
        "id":"1261198574798487554",
        "delFlag":false,
        "crtTime":"2020-05-15 02:35:47",
        "version":1,
        "budgetName":"2018年-XXX市决算",
        "year":2018,
        "area":"XXX市",
        "attaRealPath":"741833a4e1b83461ef5ceeffd92ecf7e.xls",
        "budgetType":"一般公共预算",
        "fundType":"支出",
        "budgetSubject":"二十三、债务付息支出",
        "budgetSubjectLevel":0,
        "budgetNum":0,
        "budgetAdjustNum":3917,
        "budgetFinalNum":3917,
        "makeLevel":"totalLv"
    }
]
